cropperjs/__init__.py
cropperjs/fields.py
cropperjs/models.py
cropperjs/utils.py
cropperjs/widgets.py
cropperjs/locale/pt_BR/LC_MESSAGES/django.mo
cropperjs/locale/pt_BR/LC_MESSAGES/django.po
cropperjs/static/css/cropper.extra.css
cropperjs/static/css/cropper.min.css
cropperjs/static/img/icon-reset.png
cropperjs/static/img/icon-rotate-left.png
cropperjs/static/img/icon-rotate-right.png
cropperjs/static/js/cropper.extra.js
cropperjs/static/js/cropper.min.js
cropperjs/templates/cropperjs/widgets/cropperjs.html
django_cropperjs-0.0.5.dist-info/METADATA
django_cropperjs-0.0.5.dist-info/RECORD
django_cropperjs-0.0.5.dist-info/WHEEL
django_cropperjs-0.0.5.dist-info/top_level.txt
